cagged/__init__.py
cagged/__main__.py
cagged/analyzer/__init__.py
cagged/analyzer/analyzer.py
cagged/analyzer/metadata/__init__.py
cagged/analyzer/metadata/detector.py
cagged/analyzer/metadata/empty_information.py
cagged/analyzer/metadata/npm/__init__.py
cagged/analyzer/metadata/npm/empty_information.py
cagged/analyzer/metadata/npm/potentially_compromised_email_domain.py
cagged/analyzer/metadata/npm/release_zero.py
cagged/analyzer/metadata/npm/typosquatting.py
cagged/analyzer/metadata/potentially_compromised_email_domain.py
cagged/analyzer/metadata/pypi/__init__.py
cagged/analyzer/metadata/pypi/empty_information.py
cagged/analyzer/metadata/pypi/potentially_compromised_email_domain.py
cagged/analyzer/metadata/pypi/release_zero.py
cagged/analyzer/metadata/pypi/repository_integrity_mismatch.py
cagged/analyzer/metadata/pypi/single_python_file.py
cagged/analyzer/metadata/pypi/typosquatting.py
cagged/analyzer/metadata/release_zero.py
cagged/analyzer/metadata/repository_integrity_mismatch.py
cagged/analyzer/metadata/resources/top_npm_packages.json
cagged/analyzer/metadata/resources/top_pypi_packages.json
cagged/analyzer/metadata/typosquatting.py
cagged/analyzer/sourcecode/__init__.py
cagged/analyzer/sourcecode/cmd-overwrite.yml
cagged/analyzer/sourcecode/code-execution.yml
cagged/analyzer/sourcecode/download-executable.yml
cagged/analyzer/sourcecode/exec-base64.yml
cagged/analyzer/sourcecode/exfiltrate-sensitive-data.yml
cagged/analyzer/sourcecode/npm-exec-base64.yml
cagged/analyzer/sourcecode/npm-install-script.yml
cagged/analyzer/sourcecode/npm-serialize-environment.yml
cagged/analyzer/sourcecode/npm-silent-process-execution.yml
cagged/analyzer/sourcecode/obfuscation.yml
cagged/analyzer/sourcecode/shady-links.yml
cagged/analyzer/sourcecode/silent-process-execution.yml
cagged/analyzer/sourcecode/steganography.yml
cagged/cli.py
cagged/dynamic/__init__.py
cagged/dynamic/analyze.py
cagged/ecosystems.py
cagged/misc.py
cagged/ml/__init__.py
cagged/ml/analyze.py
cagged-0.1.8.dist-info/METADATA
cagged-0.1.8.dist-info/WHEEL
cagged-0.1.8.dist-info/entry_points.txt
cagged-0.1.8.dist-info/RECORD
