Metadata-Version: 2.1
Name: cagged
Version: 0.1.8
Summary: 
Author: Родион Гудзь
Author-email: rodion@gudz.ml
Requires-Python: >=3.10,<4.0
Classifier: Programming Language :: Python :: 3
Classifier: Programming Language :: Python :: 3.10
Classifier: Programming Language :: Python :: 3.11
Requires-Dist: docker (>=6.0.1,<7.0.0)
Requires-Dist: joblib (>=1.2.0,<2.0.0)
Requires-Dist: pandas (>=1.5.3,<2.0.0)
Requires-Dist: prettytable (>=3.6.0,<4.0.0)
Requires-Dist: pygit2 (>=1.11.1,<2.0.0)
Requires-Dist: python-whois (>=0.8.0,<0.9.0)
Requires-Dist: pyyaml (>=6.0,<7.0)
Requires-Dist: requests (>=2.28.2,<3.0.0)
Requires-Dist: rich (>=13.3.3,<14.0.0)
Requires-Dist: rich-click (>=1.6.1,<2.0.0)
Requires-Dist: scikit-learn (>=1.2.2,<2.0.0)
Requires-Dist: semantic-version (>=2.10.0,<3.0.0)
Requires-Dist: semgrep (>=1.15.0,<2.0.0)
Requires-Dist: tarsafe (>=0.0.5,<0.0.6)
Requires-Dist: termcolor (>=2.2.0,<3.0.0)
